[
    {
    "name":{
        "firstName":"Abdalazez",
        "lastName":"Mohmmad"
    },
    "roomNumber":1,
    "bookingDateFrom":2018,
    "bookingDateTo":2019,
    "paid":true,
    "attended":false
  },
    {
    "name":{
        "firstName":"Ali",
        "lastName":"Khaled"
    },
    "roomNumber":3,
    "bookingDateFrom":2021,
    "bookingDateTo":2022,
    "paid":false,
    "attended":true
  },
    {
    "name":{
        "firstName":"Fhd",
        "lastName":"Ahmad"
    },
    "roomNumber":5,
    "bookingDateFrom":2011,
    "bookingDateTo":2015,
    "paid":true,
    "attended":false
  },
    {
    "name":{
        "firstName":"slman",
        "lastName":"Abdalazez"
    },
    "roomNumber":7,
    "bookingDateFrom":2022,
    "bookingDateTo":2023,
    "paid":true,
    "attended":false
  }
]